[
    {
        "question": "神经网络在图像识别中起到什么作用？它是如何处理图像数据的？",
        "answer": "神经网络在图像识别中的作用是什么？<|sep|>神经网络如何处理图像数据？"
    },
    {
        "question": "卷积神经网络（CNN）是如何工作的？它与全连接神经网络有什么区别？",
        "answer": "卷积神经网络（CNN）是如何工作的？<|sep|>CNN与全连接神经网络有什么区别？"
    },
    {
        "question": "深度学习中的反向传播算法是用来做什么的？它是如何更新权重的？",
        "answer": "深度学习中的反向传播算法是用来做什么的？<|sep|>反向传播如何更新神经网络的权重？"
    },
    {
        "question": "什么是循环神经网络（RNN）？它在自然语言处理中有哪些应用？",
        "answer": "什么是循环神经网络（RNN）？<|sep|>RNN在自然语言处理中的应用有哪些？"
    },
    {
        "question": "激活函数有哪些类型？它们的作用是什么？",
        "answer": "激活函数有哪些类型？<|sep|>激活函数作用是什么？"
    }
]